kwipy
