Metadata-Version: 1.1
Name: kwipy
Version: 0.1.3
Summary: 
